utx/__init__.py
utx/cli/__init__.py
utx/cli/cli.py
utx/cli/fixture.py
utx/cli/func.py
utx/cli/plugin.py
utx/cli/scaffold.py
utx/cli/scaffold_web.py
utx/core/__init__.py
utx/core/css/__init__.py
utx/core/css/comparison_table_model.json
utx/core/css/concurrent_template.html
utx/core/css/custom_report.py
utx/core/css/log_template.html
utx/core/css/report.py
utx/core/css/summary_template.html
utx/core/css/summary_template_pool.html
utx/core/css/summary_template_v2.html
utx/core/css/css/monokai_sublime.min.css
utx/core/css/css/report.css
utx/core/css/fonts/SourceHanSansCN-Regular.ttf
utx/core/css/fonts/glyphicons-halflings-regular.eot
utx/core/css/fonts/glyphicons-halflings-regular.svg
utx/core/css/fonts/glyphicons-halflings-regular.ttf
utx/core/css/fonts/glyphicons-halflings-regular.woff
utx/core/css/fonts/glyphicons-halflings-regular.woff2
utx/core/css/image/arrow.png
utx/core/css/image/back.svg
utx/core/css/image/broken.png
utx/core/css/image/close.svg
utx/core/css/image/console_hover.svg
utx/core/css/image/console_normal.svg
utx/core/css/image/copy.svg
utx/core/css/image/download_log.svg
utx/core/css/image/eye.svg
utx/core/css/image/fail.svg
utx/core/css/image/less.svg
utx/core/css/image/maximize.svg
utx/core/css/image/minimize.svg
utx/core/css/image/more.svg
utx/core/css/image/open_in_new_tab.svg
utx/core/css/image/order.svg
utx/core/css/image/step_fail.svg
utx/core/css/image/step_success.svg
utx/core/css/image/success.svg
utx/core/css/image/target.png
utx/core/css/image/time.svg
utx/core/css/js/bootstrap.min.js
utx/core/css/js/highlight.min.js
utx/core/css/js/jquery-1.10.2.min.js
utx/core/css/js/jquery-lang.js
utx/core/css/js/lazyload.js
utx/core/css/js/paging.js
utx/core/css/js/report.js
utx/core/css/js/echarts/echarts.common.min.js
utx/core/css/js/echarts/pfm_charts.js
utx/core/css/js/echarts/shine.js
utx/core/css/js/langpack/zh_CN.js
utx/core/utils/__init__.py
utx/core/utils/assertions.py
utx/core/utils/error.py
utx/core/utils/hook.py
utx/core/utils/runner.py
utx-1.4.2.dist-info/LICENSE
utx-1.4.2.dist-info/METADATA
utx-1.4.2.dist-info/WHEEL
utx-1.4.2.dist-info/entry_points.txt
utx-1.4.2.dist-info/top_level.txt
utx-1.4.2.dist-info/RECORD
