Metadata-Version: 2.1
Name: utx
Version: 1.4.2
Summary: UTX will help you write ui automated tests more easily!
Home-page: https://github.com/openutx
Author: lijiawei
Author-email: jiawei.li2@qq.com
License: Apache License 2.0
Keywords: utx,airtest,pytest,selenium,ui,tools
Platform: any
Classifier: Development Status :: 5 - Production/Stable
Classifier: Environment :: Console :: Curses
Classifier: Operating System :: MacOS
Classifier: Operating System :: POSIX
Classifier: Operating System :: Microsoft :: Windows
Classifier: Programming Language :: Python :: 3 :: Only
Classifier: Programming Language :: Python :: 3.6
Classifier: Programming Language :: Python :: 3.7
Classifier: Programming Language :: Python :: 3.8
Classifier: Programming Language :: Python :: 3.9
Classifier: Programming Language :: Python :: Implementation :: CPython
License-File: LICENSE
Requires-Dist: airtest >=1.3.1
Requires-Dist: tenacity
Requires-Dist: allure-pytest
Requires-Dist: pocoui
Requires-Dist: tidevice
Requires-Dist: faker
Requires-Dist: jmespath
Requires-Dist: loguru
Requires-Dist: pytest-xdist
Requires-Dist: PyYAML
Requires-Dist: allure-python-commons
Requires-Dist: pytest-rerunfailures
Requires-Dist: pyOpenSSL
Requires-Dist: selenium ~=3.14.0
Requires-Dist: tqdm
Requires-Dist: popups
Requires-Dist: ntplib
Requires-Dist: pytz
